jiractl.py
create/__init__.py
create/comment.py
create/create.py
create/issue.py
get/__init__.py
get/get.py
get/issue.py
get/issues.py
get/users.py
jira_config/__init__.py
jira_config/config.py
jira_config/remove.py
jira_config/set.py
jira_config/show.py
jiractl_shared_functions/__init__.py
jiractl_shared_functions/configuration_functions.py
jiractl_shared_functions/exceptions.py
update/__init__.py
update/issue.py
update/update.py
fancy_jira-0.1.1.dist-info/LICENSE
fancy_jira-0.1.1.dist-info/METADATA
fancy_jira-0.1.1.dist-info/WHEEL
fancy_jira-0.1.1.dist-info/entry_points.txt
fancy_jira-0.1.1.dist-info/top_level.txt
fancy_jira-0.1.1.dist-info/RECORD
