Metadata-Version: 2.1
Name: fancy-jira
Version: 0.1.1
Home-page: https://fancywhale.ca/
Author: Gui Martins
Author-email: gmartins@fancywhale.ca
License-File: LICENSE
Requires-Dist: click
Requires-Dist: requests
Requires-Dist: rich
Requires-Dist: PyYAML
Requires-Dist: tabulate
